{
  "version": "0.3.14-fixed",
  "steps": [
    {
      "tag": "UpdateArgument",
      "location": {
        "tag": "Directive",
        "path": {
          "tag": "Field",
          "model": "EnvironmentMember",
          "field": "id"
        },
        "directive": "default"
      },
      "argument": "",
      "newValue": "cuid()"
    },
    {
      "tag": "UpdateArgument",
      "location": {
        "tag": "Directive",
        "path": {
          "tag": "Field",
          "model": "Environment",
          "field": "id"
        },
        "directive": "default"
      },
      "argument": "",
      "newValue": "cuid()"
    }
  ]
}